opentelemetry/instrumentation/botocore/__init__.py
opentelemetry/instrumentation/botocore/environment_variables.py
opentelemetry/instrumentation/botocore/package.py
opentelemetry/instrumentation/botocore/utils.py
opentelemetry/instrumentation/botocore/version.py
opentelemetry/instrumentation/botocore/extensions/__init__.py
opentelemetry/instrumentation/botocore/extensions/_messaging.py
opentelemetry/instrumentation/botocore/extensions/bedrock.py
opentelemetry/instrumentation/botocore/extensions/bedrock_utils.py
opentelemetry/instrumentation/botocore/extensions/dynamodb.py
opentelemetry/instrumentation/botocore/extensions/lmbd.py
opentelemetry/instrumentation/botocore/extensions/secretsmanager.py
opentelemetry/instrumentation/botocore/extensions/sfns.py
opentelemetry/instrumentation/botocore/extensions/sns.py
opentelemetry/instrumentation/botocore/extensions/sqs.py
opentelemetry/instrumentation/botocore/extensions/types.py
opentelemetry_instrumentation_botocore-0.60b0.dist-info/METADATA
opentelemetry_instrumentation_botocore-0.60b0.dist-info/WHEEL
opentelemetry_instrumentation_botocore-0.60b0.dist-info/entry_points.txt
opentelemetry_instrumentation_botocore-0.60b0.dist-info/licenses/LICENSE
opentelemetry_instrumentation_botocore-0.60b0.dist-info/RECORD
